check_oldies/__init__.py
check_oldies/annotations.py
check_oldies/branches.py
check_oldies/check_branches.py
check_oldies/check_fixmes.py
check_oldies/commands.py
check_oldies/configuration.py
check_oldies/forget_me_not.py
check_oldies/githost.py
check_oldies/xunit.py
check_oldies-0.8.10.dist-info/LICENSE.txt
check_oldies-0.8.10.dist-info/METADATA
check_oldies-0.8.10.dist-info/WHEEL
check_oldies-0.8.10.dist-info/entry_points.txt
check_oldies-0.8.10.dist-info/top_level.txt
check_oldies-0.8.10.dist-info/RECORD
