Metadata-Version: 2.1
Name: check-oldies
Version: 0.8.10
Summary: Warns about unattended branches and FIXME or TODO annotations
Home-page: https://check-oldies.readthedocs.io/en/latest/
Author: Polyconseil
Author-email: opensource+check-oldies@polyconseil.fr
License: BSD-3-Clause
Project-URL: Documentation, https://check-oldies.readthedocs.io/en/latest/
Project-URL: Source, https://github.com/Polyconseil/check-oldies
Project-URL: Bug Tracker, https://github.com/Polyconseil/check-oldies/issues
Keywords: fixme todo quality
Platform: any
Classifier: Development Status :: 4 - Beta
Classifier: Environment :: Web Environment
Classifier: Intended Audience :: Developers
Classifier: License :: OSI Approved :: BSD License
Classifier: Programming Language :: Python
Classifier: Programming Language :: Python :: 3
Classifier: Programming Language :: Python :: 3 :: Only
Classifier: Programming Language :: Python :: 3.7
Classifier: Programming Language :: Python :: 3.8
Classifier: Programming Language :: Python :: 3.9
Classifier: Programming Language :: Python :: 3.10
Classifier: Programming Language :: Python :: 3.11
Requires-Python: >=3.7
License-File: LICENSE.txt
Provides-Extra: toml
Requires-Dist: toml ; extra == 'toml'
